{"User.c7fcd3ef-249e-4bc3-a371-8118ae6cce5c": {"id": "c7fcd3ef-249e-4bc3-a371-8118ae6cce5c", "created_at": "2024-01-17T12:51:52.891009", "updated_at": "2024-01-17T12:51:52.891014", "email": "", "password": "", "first_name": "", "last_name": "", "__class__": "User"}, "Amenity.ea6995ff-3cde-438d-9486-40988e1be704": {"id": "ea6995ff-3cde-438d-9486-40988e1be704", "created_at": "2024-01-17T12:52:46.625996", "updated_at": "2024-01-17T12:52:46.626000", "name": "", "__class__": "Amenity"}, "Amenity.f042763e-97ce-4966-b68d-8ba7a51f427d": {"id": "f042763e-97ce-4966-b68d-8ba7a51f427d", "created_at": "2024-01-17T12:54:13.895199", "updated_at": "2024-01-17T12:54:13.895204", "name": "", "__class__": "Amenity"}, "State.c4008781-6d54-4fd7-aeb9-739ab81547c7": {"id": "c4008781-6d54-4fd7-aeb9-739ab81547c7", "created_at": "2024-01-17T12:55:27.012845", "updated_at": "2024-01-17T12:55:27.012849", "name": "California", "__class__": "State"}, "State.286a4561-6ac6-4503-bdae-52dc66bb848c": {"id": "286a4561-6ac6-4503-bdae-52dc66bb848c", "created_at": "2024-01-17T12:55:27.026446", "updated_at": "2024-01-17T12:55:27.026450", "name": "Arizona", "__class__": "State"}, "Place.70c4a1fa-e61d-44e2-ba6d-6371927f6e53": {"id": "70c4a1fa-e61d-44e2-ba6d-6371927f6e53", "created_at": "2024-01-17T12:55:27.041080", "updated_at": "2024-01-17T12:55:27.041085", "city_id": 1, "user_id": 1, "name": "My little house", "number_rooms": 4, "number_bathrooms": 2, "max_guest": 10, "price_by_night": 300, "latitude": 37.773972, "longitude": -122.431297, "description": "", "amenity_ids": [], "__class__": "Place"}}